frequenz/api/assets/__init__.py
frequenz/api/assets/conftest.py
frequenz/api/assets/py.typed
frequenz/api/assets/v1/__init__.py
frequenz/api/assets/v1/assets_pb2.py
frequenz/api/assets/v1/assets_pb2.pyi
frequenz/api/assets/v1/assets_pb2_grpc.py
frequenz/api/assets/v1/assets_pb2_grpc.pyi
frequenz_api_assets-0.0.1.dist-info/LICENSE
frequenz_api_assets-0.0.1.dist-info/METADATA
frequenz_api_assets-0.0.1.dist-info/WHEEL
frequenz_api_assets-0.0.1.dist-info/top_level.txt
frequenz_api_assets-0.0.1.dist-info/RECORD
